Workbook

Sheet Ingredients
A1: Name | B1: Price | C1: Unit | D1: Supplier
A2: Mince | B2: 1.5 | C2: kg | D2: Butcher
A3: Onion | B3: 1 | C3: kg | D3: Fresh n Fruity
A4: Tomatoes | B4: 2.34 | C4: kg | D4: Saucery's
A5: Carrots | B5: 1.17 | C5: kg | D5: Hanos
A6: Pasta | B6: 0.94 | C6: kg | D6: Meatery
A7: Parmesan | B7: 5.3 | C7: kg | D7: Fresh n Fruity
A8: Olives | B8: 10 | C8: kg | D8: Fresh n Fruity
A9: Potatoes | B9: 5 | C9: kg | D9: Fresh n Fruity
A10: Celery | B10: 0.89 | C10: kg | D10: Fresh n Fruity
A11: Tomato Paste | B11: 3.75 | C11: kg | D11: Brakes
A12: Chicken Stock | B12: 0.68 | C12: l | D12: Brakes
A13: Red Wine | B13: 3.89 | C13: l | D13: Super Importers
... A21: Eggs | B21: 0.15 | C21: pcs | D21: Farm Fresh

Sheet Omelete
A1: Metric | B1: Value | D1: Συγκριτικα ανα εβοδμαδα
A2: DISH NAME | B2: Omelete
A3: EST. SALE PRICE (VAT INC) | B3: 25
A4: VAT % | B4: 0.13
A5: SALE PRICE (VAT EX) | B5: =B3 / (1 + B4) -> 22.123894
A6: FOOD COST | B6: =SUM(E12:E30) -> 19.9378
A7: FOOD COST % | B7: =B6 / B5 -> 0.90118856
A8: NET PROFIT | B8: =B5 - B6 -> 2.1860938
A11: Product Name | B11: Quantity | C11: UOM | D11: Price/Unit | E11: Total Cost
A12: Eggs | B12: 3 | C12: =IFERROR(VLOOKUP(A12, Ingredients!A:C, 3, FALSE), "") -> pcs | D12: =IFERROR(VLOOKUP(A12, Ingredients!A:D, 2, FALSE), 0) -> 0.15 | E12: =IF(OR(C12="g",C12="ml"),(B12/1000)*D12, B12*D12) -> 0.45
A13: Salt | B13: 5 | C13: g | D13: =IFERROR(VLOOKUP(A13, Ingredients!A:D, 2, FALSE), 0) -> 7 | E13: =IF(OR(C13="g",C13="ml"),(B13/1000)*D13, B13*D13) -> 0.035
A14: Red Wine | B14: 5 | C14: =IFERROR(VLOOKUP(A14, Ingredients!A:C, 3, FALSE), "") -> l | D14: =IFERROR(VLOOKUP(A14, Ingredients!A:D, 2, FALSE), 0) -> 3.89 | E14: =IF(OR(C14="g",C14="ml"),(B14/1000)*D14, B14*D14) -> 19.45
A15: Rosemary | B15: 5 | C15: g | D15: =IFERROR(VLOOKUP(A15, Ingredients!A:D, 2, FALSE), 0) -> 0.56 | E15: =IF(OR(C15="g",C15="ml"),(B15/1000)*D15, B15*D15) -> 0.0028
C16: =IFERROR(VLOOKUP(A16, Ingredients!A:C, 3, FALSE), "") | D16: =IFERROR(VLOOKUP(A16, Ingredients!A:D, 2, FALSE), 0) -> 0 | E16: =IF(OR(C16="g",C16="ml"),(B16/1000)*D16, B16*D16) -> 0
C17: =IFERROR(VLOOKUP(A17, Ingredients!A:C, 3, FALSE), "") | D17: =IFERROR(VLOOKUP(A17, Ingredients!A:D, 2, FALSE), 0) -> 0 | E17: =IF(OR(C17="g",C17="ml"),(B17/1000)*D17, B17*D17) -> 0
C18: =IFERROR(VLOOKUP(A18, Ingredients!A:C, 3, FALSE), "") | D18: =IFERROR(VLOOKUP(A18, Ingredients!A:D, 2, FALSE), 0) -> 0 | E18: =IF(OR(C18="g",C18="ml"),(B18/1000)*D18, B18*D18) -> 0
C19: =IFERROR(VLOOKUP(A19, Ingredients!A:C, 3, FALSE), "") | D19: =IFERROR(VLOOKUP(A19, Ingredients!A:D, 2, FALSE), 0) -> 0 | E19: =IF(OR(C19="g",C19="ml"),(B19/1000)*D19, B19*D19) -> 0
C20: =IFERROR(VLOOKUP(A20, Ingredients!A:C, 3, FALSE), "") | D20: =IFERROR(VLOOKUP(A20, Ingredients!A:D, 2, FALSE), 0) -> 0 | E20: =IF(OR(C20="g",C20="ml"),(B20/1000)*D20, B20*D20) -> 0
C21: =IFERROR(VLOOKUP(A21, Ingredients!A:C, 3, FALSE), "") | D21: =IFERROR(VLOOKUP(A21, Ingredients!A:D, 2, FALSE), 0) -> 0 | E21: =IF(OR(C21="g",C21="ml"),(B21/1000)*D21, B21*D21) -> 0
C22: =IFERROR(VLOOKUP(A22, Ingredients!A:C, 3, FALSE), "") | D22: =IFERROR(VLOOKUP(A22, Ingredients!A:D, 2, FALSE), 0) -> 0 | E22: =IF(OR(C22="g",C22="ml"),(B22/1000)*D22, B22*D22) -> 0
C23: =IFERROR(VLOOKUP(A23, Ingredients!A:C, 3, FALSE), "") | D23: =IFERROR(VLOOKUP(A23, Ingredients!A:D, 2, FALSE), 0) -> 0 | E23: =IF(OR(C23="g",C23="ml"),(B23/1000)*D23, B23*D23) -> 0
C24: =IFERROR(VLOOKUP(A24, Ingredients!A:C, 3, FALSE), "") | D24: =IFERROR(VLOOKUP(A24, Ingredients!A:D, 2, FALSE), 0) -> 0 | E24: =IF(OR(C24="g",C24="ml"),(B24/1000)*D24, B24*D24) -> 0
C25: =IFERROR(VLOOKUP(A25, Ingredients!A:C, 3, FALSE), "") | D25: =IFERROR(VLOOKUP(A25, Ingredients!A:D, 2, FALSE), 0) -> 0 | E25: =IF(OR(C25="g",C25="ml"),(B25/1000)*D25, B25*D25) -> 0
C26: =IFERROR(VLOOKUP(A26, Ingredients!A:C, 3, FALSE), "") | D26: =IFERROR(VLOOKUP(A26, Ingredients!A:D, 2, FALSE), 0) -> 0 | E26: =IF(OR(C26="g",C26="ml"),(B26/1000)*D26, B26*D26) -> 0
C27: =IFERROR(VLOOKUP(A27, Ingredients!A:C, 3, FALSE), "") | D27: =IFERROR(VLOOKUP(A27, Ingredients!A:D, 2, FALSE), 0) -> 0 | E27: =IF(OR(C27="g",C27="ml"),(B27/1000)*D27, B27*D27) -> 0
... C30: =IFERROR(VLOOKUP(A30, Ingredients!A:C, 3, FALSE), "") | D30: =IFERROR(VLOOKUP(A30, Ingredients!A:D, 2, FALSE), 0) -> 0 | E30: =IF(OR(C30="g",C30="ml"),(B30/1000)*D30, B30*D30) -> 0

Sheet Recipe
A1: Metric | B1: Value
A2: DISH NAME | B2: Omelete
A3: EST. SALE PRICE (VAT INC) | B3: 10
A4: VAT % | B4: 0
A5: SALE PRICE (VAT EX) | B5: =B3 / (1 + B4) -> 10
A6: FOOD COST | B6: =SUM(E12:E30) -> 2.4025
A7: FOOD COST % | B7: =B6 / B5 -> 0.24025
A8: NET PROFIT | B8: =B5 - B6 -> 7.5975
A11: Product Name | B11: Quantity | C11: UOM | D11: Price/Unit | E11: Total Cost
A12: Eggs | B12: 5 | C12: =IFERROR(VLOOKUP(A12, Ingredients!A:C, 3, FALSE), "") -> pcs | D12: =IFERROR(VLOOKUP(A12, Ingredients!A:D, 2, FALSE), 0) -> 0.15 | E12: =IF(OR(C12="g",C12="ml"),(B12/1000)*D12, B12*D12) -> 0.75
A13: Chicken Stock | B13: 1 | C13: =IFERROR(VLOOKUP(A13, Ingredients!A:C, 3, FALSE), "") -> l | D13: =IFERROR(VLOOKUP(A13, Ingredients!A:D, 2, FALSE), 0) -> 0.68 | E13: =IF(OR(C13="g",C13="ml"),(B13/1000)*D13, B13*D13) -> 0.68
A14: Red Wine | B14: 250 | C14: ml | D14: =IFERROR(VLOOKUP(A14, Ingredients!A:D, 2, FALSE), 0) -> 3.89 | E14: =IF(OR(C14="g",C14="ml"),(B14/1000)*D14, B14*D14) -> 0.9725
C15: =IFERROR(VLOOKUP(A15, Ingredients!A:C, 3, FALSE), "") | D15: =IFERROR(VLOOKUP(A15, Ingredients!A:D, 2, FALSE), 0) -> 0 | E15: =IF(OR(C15="g",C15="ml"),(B15/1000)*D15, B15*D15) -> 0
C16: =IFERROR(VLOOKUP(A16, Ingredients!A:C, 3, FALSE), "") | D16: =IFERROR(VLOOKUP(A16, Ingredients!A:D, 2, FALSE), 0) -> 0 | E16: =IF(OR(C16="g",C16="ml"),(B16/1000)*D16, B16*D16) -> 0
C17: =IFERROR(VLOOKUP(A17, Ingredients!A:C, 3, FALSE), "") | D17: =IFERROR(VLOOKUP(A17, Ingredients!A:D, 2, FALSE), 0) -> 0 | E17: =IF(OR(C17="g",C17="ml"),(B17/1000)*D17, B17*D17) -> 0
C18: =IFERROR(VLOOKUP(A18, Ingredients!A:C, 3, FALSE), "") | D18: =IFERROR(VLOOKUP(A18, Ingredients!A:D, 2, FALSE), 0) -> 0 | E18: =IF(OR(C18="g",C18="ml"),(B18/1000)*D18, B18*D18) -> 0
C19: =IFERROR(VLOOKUP(A19, Ingredients!A:C, 3, FALSE), "") | D19: =IFERROR(VLOOKUP(A19, Ingredients!A:D, 2, FALSE), 0) -> 0 | E19: =IF(OR(C19="g",C19="ml"),(B19/1000)*D19, B19*D19) -> 0
C20: =IFERROR(VLOOKUP(A20, Ingredients!A:C, 3, FALSE), "") | D20: =IFERROR(VLOOKUP(A20, Ingredients!A:D, 2, FALSE), 0) -> 0 | E20: =IF(OR(C20="g",C20="ml"),(B20/1000)*D20, B20*D20) -> 0
C21: =IFERROR(VLOOKUP(A21, Ingredients!A:C, 3, FALSE), "") | D21: =IFERROR(VLOOKUP(A21, Ingredients!A:D, 2, FALSE), 0) -> 0 | E21: =IF(OR(C21="g",C21="ml"),(B21/1000)*D21, B21*D21) -> 0
C22: =IFERROR(VLOOKUP(A22, Ingredients!A:C, 3, FALSE), "") | D22: =IFERROR(VLOOKUP(A22, Ingredients!A:D, 2, FALSE), 0) -> 0 | E22: =IF(OR(C22="g",C22="ml"),(B22/1000)*D22, B22*D22) -> 0
C23: =IFERROR(VLOOKUP(A23, Ingredients!A:C, 3, FALSE), "") | D23: =IFERROR(VLOOKUP(A23, Ingredients!A:D, 2, FALSE), 0) -> 0 | E23: =IF(OR(C23="g",C23="ml"),(B23/1000)*D23, B23*D23) -> 0
C24: =IFERROR(VLOOKUP(A24, Ingredients!A:C, 3, FALSE), "") | D24: =IFERROR(VLOOKUP(A24, Ingredients!A:D, 2, FALSE), 0) -> 0 | E24: =IF(OR(C24="g",C24="ml"),(B24/1000)*D24, B24*D24) -> 0
C25: =IFERROR(VLOOKUP(A25, Ingredients!A:C, 3, FALSE), "") | D25: =IFERROR(VLOOKUP(A25, Ingredients!A:D, 2, FALSE), 0) -> 0 | E25: =IF(OR(C25="g",C25="ml"),(B25/1000)*D25, B25*D25) -> 0
C26: =IFERROR(VLOOKUP(A26, Ingredients!A:C, 3, FALSE), "") | D26: =IFERROR(VLOOKUP(A26, Ingredients!A:D, 2, FALSE), 0) -> 0 | E26: =IF(OR(C26="g",C26="ml"),(B26/1000)*D26, B26*D26) -> 0
... C30: =IFERROR(VLOOKUP(A30, Ingredients!A:C, 3, FALSE), "") | D30: =IFERROR(VLOOKUP(A30, Ingredients!A:D, 2, FALSE), 0) -> 0 | E30: =IF(OR(C30="g",C30="ml"),(B30/1000)*D30, B30*D30) -> 0

Sheet Sheet1
